<?xml version="1.0" encoding="UTF-8"?>
<!--+
    | Maven project description for the AstroGrid registry common components.
    +-->
<project
  xmlns:xsi="http://www.w3.org/2001/XMLSchema-instance"
  xsi:noNamespaceSchemaLocation="maven-project.xsd">
    <!--+
        | Extend the top level project descriptor.
        +-->
    <extend>${basedir}/../maven/project.xml</extend>

    <!--+
        | The current version of the Maven project descriptor.
        +-->
    <pomVersion>3</pomVersion>

    <!--+
        | The short name of the project.
        | This is used when naming jars and distribution files.
        +-->
    <id>astrogrid-registry-common</id>

    <!--+
        | The full name of the project.
        | This is used when generating JavaDoc titles.
        +-->
    <name>AstroGrid registry common</name>

    <!--+
        | The Java package name of the project.
        | This value is used when generating JavaDoc.
        +-->
    <package>org.astrogrid.registry.common</package>

    <!--+
        | Optional.
        | A detailed description of the project.
        | This element is usually specified as CDATA to enable the use of HTML tags within the description.
        | This description is used to generate the front page of the project's web site. 
        +-->
    <description>
        <![CDATA[
	<p>
		The Common area are what is common between both the Client and Server areas.  Registry also uses Castor to generate
		java objects which are used both in the common and server areas.
	</p>
	<section name="Builds">
		<p>			
			Here are the maven goals for building the registry, it has a one extra goal compared to the other sub-projects.
			<ul>
				<li>clean - cleans out and removes all previous builds.</li>
				<li>install-snapshot - Builds all the necessry jar and war files.</li>
				<li>astrogrid-deploy-snapshot - Builds and deploys the snapshot onto the repository.</li>
				<li>astrogrid-deploy-site - Generates reports and documents to be deployed on the site repository.</li>
				<li>generate-castor - generates the castor objects.  This is automatically done though because it is done
				as a pre-goal to java:compile.</li>				
			</ul>
		</p>
	</section>
		]]>        
</description>

    <!--+
        | A short description of the project.
        | The short description should be limited to a single line.
        +-->
    <shortDescription>Registry classes used by both the client and server</shortDescription>

    <!--+
        | Our cvs repository location.
        +-->
    <repository>
        <connection>
            scm:cvs:pserver:anoncvs@cvs.astrogrid.org:/devel:astrogrid/registry/common
        </connection>
        <developerConnection>
            scm:cvs:ext:${maven.username}@cvs.astrogrid.org:/devel:astrogrid/registry/common
        </developerConnection>
    </repository>

    <!--+
        | The external dependencies required to build and test the project.
        +-->
    <dependencies>
        
        <dependency>
            <artifactId>astrogrid-common</artifactId>
            <groupId>org.astrogrid</groupId>
            <version>SNAPSHOT</version>
            <properties>
                <war.bundle>true</war.bundle>
            </properties>
        </dependency>

        
        <!-- helper for object models -->
        <dependency>
        	<artifactId>commons-jxpath</artifactId>
            <groupId>commons-jxpath</groupId>
            <version>1.1</version>
        </dependency>
        
        <!-- required by castor -->
        <dependency>
            <artifactId>castor</artifactId>
            <groupId>castor</groupId>
            <version>0.9.5</version>
            <jar>castor-0.9.5-xml.jar</jar>
        </dependency>
            
        <dependency>
        	<id>xerces</id>
            <version>2.4.0</version>
            <properties>
            	<war.bundle>true</war.bundle>
            </properties>
        </dependency>
        
        <dependency>
       		<id>xml-apis</id>
          	<version>1.0.b2</version>
          	<properties>
          		<war.bundle>true</war.bundle>
          	</properties>
        </dependency>
        

    </dependencies>

    <!--+
        | The build properties for our project.
        +-->
    <build>
        <!--+
            | The location of our Java source code.
            +-->
        <sourceDirectory>src/java</sourceDirectory>
        <!--+
            | The location of our JUnit source code.
            +-->
        <unitTestSourceDirectory>src/junit</unitTestSourceDirectory>
        <!--+
            | Our JUnit test classes.
            +-->
        <unitTest>
            <!--+
                | Which tests to include.
                +-->
            <includes>
                <include>**/*JUnitTest.java</include>
            </includes>
            
            <!--+
                | The resources for our tests.
            <resources>
                <resource>
                </resource>
            </resources>
                +-->
        </unitTest>
    </build>

</project>
