<?xml version="1.0" encoding="utf-8"?>
<Select xmlns:xsd="http://www.w3.org/2001/XMLSchema" xmlns:xsi="http://www.w3.org/2001/XMLSchema-instance" xmlns="http://www.ivoa.net/xml/ADQL/v0.7.4">
  <SelectionList>
    <Item xsi:type="allSelectionItemType" />
  </SelectionList>
  <From>
    <Table xsi:type="tableType" Name="CASU_INT_DSA" Alias="casu" />
  </From>
  <Where>
    <Condition xsi:type="regionSearchType">
      <Region xmlns:q1="urn:nvo-region" xsi:type="q1:circleType" coord_system_id="">
        <q1:Center ID="" coord_system_id="">
          <Pos2Vector xmlns="urn:nvo-coords">
            <Name>Ra Dec</Name>
            <CoordValue>
              <Value>
                <double>56.75</double>
                <double>23.867</double>
              </Value>
            </CoordValue>
          </Pos2Vector>
        </q1:Center>
        <q1:Radius>0.3</q1:Radius>
      </Region>
    </Condition>
  </Where>
</Select>
